<?xml version="1.0" encoding="utf-8" ?>

<MarvellSWVolCalibrationConfig>
    <Version>1.0</Version>

    <PlaybackVolumeConfig>
        <Step>0.5</Step>

        <!--optional: Step-->

        <Stream identifier="AUDIO_STREAM_VOICE_CALL" range="0:5">

            <!--optional: range-->

            <Device identifier="AUDIO_DEVICE_OUT_EARPIECE">

                <Format identifier=".DEFAULT">
                    <Value index="0">0x5a</Value>

                    <Value index="1">0x60</Value>

                    <Value index="2">0x66</Value>

                    <Value index="3">0x6c</Value>

                    <Value index="4">0x72</Value>

                    <Value index="5">0x78</Value>

                </Format>
            </Device>
            <Device identifier="AUDIO_DEVICE_OUT_WIRED_HEADSET">

                <Format identifier=".DEFAULT">

                    <Value index="0">0x52</Value>

                    <Value index="1">0x58</Value>

                    <Value index="2">0x5e</Value>

                    <Value index="3">0x64</Value>

                    <Value index="4">0x6e</Value>

                    <Value index="5">0x78</Value>

                </Format>

            </Device>

            <Device identifier="AUDIO_DEVICE_OUT_SPEAKER">

                <Format identifier=".DEFAULT">

                    <Value index="0">0x50</Value>

                    <Value index="1">0x56</Value>

                    <Value index="2">0x5c</Value>

                    <Value index="3">0x64</Value>

                    <Value index="4">0x6e</Value>

                    <Value index="5">0x78</Value>

                </Format>

            </Device>

        </Stream>
        <Stream identifier="AUDIO_STREAM_VIDEO_CALL" range="0:5">

            <!--optional: range-->

            <Device identifier="AUDIO_DEVICE_OUT_SPEAKER">

                <Format identifier=".DEFAULT">
                    <Value index="0">0x5a</Value>

                    <Value index="1">0x60</Value>

                    <Value index="2">0x66</Value>

                    <Value index="3">0x6c</Value>

                    <Value index="4">0x72</Value>

                    <Value index="5">0x78</Value>

                </Format>
            </Device>
            <Device identifier="AUDIO_DEVICE_OUT_EARPIECE">

                <Format identifier=".DEFAULT">

                    <Value index="0">0x5a</Value>

                    <Value index="1">0x60</Value>

                    <Value index="2">0x66</Value>

                    <Value index="3">0x6c</Value>

                    <Value index="4">0x72</Value>

                    <Value index="5">0x78</Value>

                </Format>

            </Device>

            <Device identifier="AUDIO_DEVICE_OUT_WIRED_HEADSET">

                <Format identifier=".DEFAULT">
                    <Value index="0">0x0</Value>

                    <Value index="1">0x28</Value>

                    <Value index="2">0x3c</Value>

                    <Value index="3">0x50</Value>

                    <Value index="4">0x64</Value>

                    <Value index="5">0x78</Value>

                </Format>
            </Device>
        </Stream>
        <Stream identifier="AUDIO_STREAM_SYSTEM" range="0:7">

            <Device identifier="AUDIO_DEVICE_OUT_SPEAKER">

                <Format identifier=".mp3">

                    <Value index="0">0x0</Value>

                    <Value index="1">0x46</Value>

                    <Value index="2">0x50</Value>

                    <Value index="3">0x58</Value>

                    <Value index="4">0x60</Value>

                    <Value index="5">0x68</Value>

                    <Value index="6">0x70</Value>

                    <Value index="7">0x78</Value>

                </Format>

                <Format identifier=".ogg">

                    <Value index="0">0x0</Value>

                    <Value index="1">0x46</Value>

                    <Value index="2">0x50</Value>

                    <Value index="3">0x58</Value>

                    <Value index="4">0x60</Value>

                    <Value index="5">0x68</Value>

                    <Value index="6">0x70</Value>

                    <Value index="7">0x78</Value>

                </Format>

                <Format identifier=".aac">

                    <Value index="0">0x0</Value>

                    <Value index="1">0x46</Value>

                    <Value index="2">0x50</Value>

                    <Value index="3">0x58</Value>

                    <Value index="4">0x60</Value>

                    <Value index="5">0x68</Value>

                    <Value index="6">0x70</Value>

                    <Value index="7">0x78</Value>

                </Format>

                <Format identifier=".mid">

                    <Value index="0">0x0</Value>

                    <Value index="1">0x46</Value>

                    <Value index="2">0x50</Value>

                    <Value index="3">0x58</Value>

                    <Value index="4">0x60</Value>

                    <Value index="5">0x68</Value>

                    <Value index="6">0x70</Value>

                    <Value index="7">0x78</Value>

                </Format>

                <Format identifier=".amr">

                    <Value index="0">0x0</Value>

                    <Value index="1">0x46</Value>

                    <Value index="2">0x50</Value>

                    <Value index="3">0x58</Value>

                    <Value index="4">0x60</Value>

                    <Value index="5">0x68</Value>

                    <Value index="6">0x70</Value>

                    <Value index="7">0x78</Value>

                </Format>

                <Format identifier=".wav">

                    <Value index="0">0x0</Value>

                    <Value index="1">0x46</Value>

                    <Value index="2">0x50</Value>

                    <Value index="3">0x58</Value>

                    <Value index="4">0x60</Value>

                    <Value index="5">0x68</Value>

                    <Value index="6">0x70</Value>

                    <Value index="7">0x78</Value>

                </Format>

                <Format identifier=".DEFAULT">
                    <Value index="0">0x0</Value>

                    <Value index="1">0x46</Value>

                    <Value index="2">0x50</Value>

                    <Value index="3">0x58</Value>

                    <Value index="4">0x60</Value>

                    <Value index="5">0x68</Value>

                    <Value index="6">0x70</Value>

                    <Value index="7">0x78</Value>

                </Format>
            </Device>
            <Device identifier="AUDIO_DEVICE_OUT_WIRED_HEADSET">

                <Format identifier=".ogg">

                    <Value index="0">0x0</Value>

                    <Value index="1">0x2e</Value>

                    <Value index="2">0x36</Value>

                    <Value index="3">0x44</Value>

                    <Value index="4">0x4e</Value>

                    <Value index="5">0x54</Value>

                    <Value index="6">0x5a</Value>

                    <Value index="7">0x60</Value>

                </Format>

                <Format identifier=".amr">

                    <Value index="0">0x0</Value>

                    <Value index="1">0x2e</Value>

                    <Value index="2">0x36</Value>

                    <Value index="3">0x44</Value>

                    <Value index="4">0x4e</Value>

                    <Value index="5">0x54</Value>

                    <Value index="6">0x5a</Value>

                    <Value index="7">0x60</Value>

                </Format>

                <Format identifier=".wav">

                    <Value index="0">0x0</Value>

                    <Value index="1">0x2e</Value>

                    <Value index="2">0x36</Value>

                    <Value index="3">0x44</Value>

                    <Value index="4">0x4e</Value>

                    <Value index="5">0x54</Value>

                    <Value index="6">0x5a</Value>

                    <Value index="7">0x60</Value>

                </Format>

                <Format identifier=".mp3">

                    <Value index="0">0x0</Value>

                    <Value index="1">0x2e</Value>

                    <Value index="2">0x36</Value>

                    <Value index="3">0x44</Value>

                    <Value index="4">0x4e</Value>

                    <Value index="5">0x54</Value>

                    <Value index="6">0x5a</Value>

                    <Value index="7">0x60</Value>

                </Format>

                <Format identifier=".aac">

                    <Value index="0">0x0</Value>

                    <Value index="1">0x2e</Value>

                    <Value index="2">0x36</Value>

                    <Value index="3">0x44</Value>

                    <Value index="4">0x4e</Value>

                    <Value index="5">0x54</Value>

                    <Value index="6">0x5a</Value>

                    <Value index="7">0x60</Value>


                </Format>

                <Format identifier=".mid">

                    <Value index="0">0x0</Value>

                    <Value index="1">0x2e</Value>

                    <Value index="2">0x36</Value>

                    <Value index="3">0x44</Value>

                    <Value index="4">0x4e</Value>

                    <Value index="5">0x54</Value>

                    <Value index="6">0x5a</Value>

                    <Value index="7">0x60</Value>


                </Format>

                <Format identifier=".DEFAULT">
                    <Value index="0">0x0</Value>

                    <Value index="1">0x2e</Value>

                    <Value index="2">0x36</Value>

                    <Value index="3">0x44</Value>

                    <Value index="4">0x4e</Value>

                    <Value index="5">0x54</Value>

                    <Value index="6">0x5a</Value>

                    <Value index="7">0x60</Value>

                </Format>
            </Device>
            <Device identifier="AUDIO_DEVICE_OUT_WIRED_HEADPHONE">

                <Format identifier=".ogg">

                    <Value index="0">0x0</Value>

                    <Value index="1">0x2e</Value>

                    <Value index="2">0x34</Value>

                    <Value index="3">0x3e</Value>

                    <Value index="4">0x48</Value>

                    <Value index="5">0x52</Value>

                    <Value index="6">0x5c</Value>

                    <Value index="7">0x66</Value>

                </Format>

                <Format identifier=".amr">

                    <Value index="0">0x0</Value>

                    <Value index="1">0x2e</Value>

                    <Value index="2">0x34</Value>

                    <Value index="3">0x3e</Value>

                    <Value index="4">0x48</Value>

                    <Value index="5">0x52</Value>

                    <Value index="6">0x5c</Value>

                    <Value index="7">0x66</Value>

                </Format>

                <Format identifier=".wav">

                    <Value index="0">0x0</Value>

                    <Value index="1">0x2e</Value>

                    <Value index="2">0x34</Value>

                    <Value index="3">0x3e</Value>

                    <Value index="4">0x48</Value>

                    <Value index="5">0x52</Value>

                    <Value index="6">0x5c</Value>

                    <Value index="7">0x66</Value>

                </Format>

                <Format identifier=".mp3">

                    <Value index="0">0x0</Value>

                    <Value index="1">0x2e</Value>

                    <Value index="2">0x34</Value>

                    <Value index="3">0x3e</Value>

                    <Value index="4">0x48</Value>

                    <Value index="5">0x52</Value>

                    <Value index="6">0x5c</Value>

                    <Value index="7">0x66</Value>

                </Format>

                <Format identifier=".DEFAULT">
                    <Value index="0">0x0</Value>

                    <Value index="1">0x2e</Value>

                    <Value index="2">0x34</Value>

                    <Value index="3">0x3e</Value>

                    <Value index="4">0x48</Value>

                    <Value index="5">0x52</Value>

                    <Value index="6">0x5c</Value>

                    <Value index="7">0x66</Value>

                </Format>

                <Format identifier=".aac">

                    <Value index="0">0x0</Value>

                    <Value index="1">0x2e</Value>

                    <Value index="2">0x34</Value>

                    <Value index="3">0x3e</Value>

                    <Value index="4">0x48</Value>

                    <Value index="5">0x52</Value>

                    <Value index="6">0x5c</Value>

                    <Value index="7">0x66</Value>

                </Format>

                <Format identifier=".mid">

                    <Value index="0">0x0</Value>

                    <Value index="1">0x2e</Value>

                    <Value index="2">0x34</Value>

                    <Value index="3">0x3e</Value>

                    <Value index="4">0x48</Value>

                    <Value index="5">0x52</Value>

                    <Value index="6">0x5c</Value>

                    <Value index="7">0x66</Value>

                </Format>
            </Device>
        </Stream>
        <Stream identifier="AUDIO_STREAM_RING" range="0:7">

            <Device identifier="AUDIO_DEVICE_OUT_SPEAKER">

                <Format identifier=".mp3">

                    <Value index="0">0x0</Value>

                    <Value index="1">0x14</Value>

                    <Value index="2">0x22</Value>

                    <Value index="3">0x30</Value>

                    <Value index="4">0x3e</Value>

                    <Value index="5">0x4c</Value>

                    <Value index="6">0x5a</Value>

                    <Value index="7">0x68</Value>

                </Format>

                <Format identifier=".aac">

                    <Value index="0">0x0</Value>

                    <Value index="1">0x14</Value>

                    <Value index="2">0x22</Value>

                    <Value index="3">0x30</Value>

                    <Value index="4">0x3e</Value>

                    <Value index="5">0x4c</Value>

                    <Value index="6">0x5a</Value>

                    <Value index="7">0x68</Value>

                </Format>

                <Format identifier=".ogg">

                    <Value index="0">0x0</Value>

                    <Value index="1">0x14</Value>

                    <Value index="2">0x22</Value>

                    <Value index="3">0x30</Value>

                    <Value index="4">0x3e</Value>

                    <Value index="5">0x4c</Value>

                    <Value index="6">0x5a</Value>

                    <Value index="7">0x68</Value>

                </Format>

                <Format identifier=".amr">

                    <Value index="0">0x0</Value>

                    <Value index="1">0x24</Value>

                    <Value index="2">0x30</Value>

                    <Value index="3">0x3c</Value>

                    <Value index="4">0x47</Value>

                    <Value index="5">0x54</Value>

                    <Value index="6">0x60</Value>

                    <Value index="7">0x6d</Value>

                </Format>

                <Format identifier=".DEFAULT">

                    <Value index="0">0x0</Value>

                    <Value index="1">0x14</Value>

                    <Value index="2">0x22</Value>

                    <Value index="3">0x30</Value>

                    <Value index="4">0x3e</Value>

                    <Value index="5">0x4c</Value>

                    <Value index="6">0x5a</Value>

                    <Value index="7">0x68</Value>

                </Format>

                <Format identifier=".mid">

                    <Value index="0">0x0</Value>

                    <Value index="1">0x24</Value>

                    <Value index="2">0x2e</Value>

                    <Value index="3">0x38</Value>

                    <Value index="4">0x42</Value>

                    <Value index="5">0x4c</Value>

                    <Value index="6">0x58</Value>

                    <Value index="7">0x64</Value>

                </Format>

            </Device>

            <Device identifier="AUDIO_DEVICE_OUT_WIRED_HEADSET">

                <Format identifier=".DEFAULT">
                    <!--default format-->

                    <Value index="0">0x0</Value>

                    <Value index="1">0x24</Value>

                    <Value index="2">0x32</Value>

                    <Value index="3">0x40</Value>

                    <Value index="4">0x4e</Value>

                    <Value index="5">0x5c</Value>

                    <Value index="6">0x6a</Value>

                    <Value index="7">0x78</Value>

                </Format>

                <Format identifier=".mp3">

                    <Value index="0">0x0</Value>

                    <Value index="1">0x24</Value>

                    <Value index="2">0x32</Value>

                    <Value index="3">0x40</Value>

                    <Value index="4">0x4e</Value>

                    <Value index="5">0x5c</Value>

                    <Value index="6">0x6a</Value>

                    <Value index="7">0x78</Value>

                </Format>

                <Format identifier=".aac">

                    <Value index="0">0x0</Value>

                    <Value index="1">0x24</Value>

                    <Value index="2">0x32</Value>

                    <Value index="3">0x40</Value>

                    <Value index="4">0x4e</Value>

                    <Value index="5">0x5c</Value>

                    <Value index="6">0x6a</Value>

                    <Value index="7">0x78</Value>

                </Format>

                <Format identifier=".ogg">

                    <Value index="0">0x0</Value>

                    <Value index="1">0x24</Value>

                    <Value index="2">0x32</Value>

                    <Value index="3">0x40</Value>

                    <Value index="4">0x4e</Value>

                    <Value index="5">0x5c</Value>

                    <Value index="6">0x6a</Value>

                    <Value index="7">0x78</Value>

                </Format>
            </Device>
            <CombinedDevices identifier1="AUDIO_DEVICE_OUT_SPEAKER" identifier2="AUDIO_DEVICE_OUT_WIRED_HEADSET">

                <Format identifier=".mp3">

                    <Value index="0">0x0</Value>

                    <Value index="1">0x14</Value>

                    <Value index="2">0x22</Value>

                    <Value index="3">0x30</Value>

                    <Value index="4">0x3e</Value>

                    <Value index="5">0x4c</Value>

                    <Value index="6">0x5a</Value>

                    <Value index="7">0x68</Value>

                </Format>

                <Format identifier=".aac">

                    <Value index="0">0x0</Value>

                    <Value index="1">0x14</Value>

                    <Value index="2">0x22</Value>

                    <Value index="3">0x30</Value>

                    <Value index="4">0x3e</Value>

                    <Value index="5">0x4c</Value>

                    <Value index="6">0x5a</Value>

                    <Value index="7">0x68</Value>

                </Format>

                <Format identifier=".ogg">

                    <Value index="0">0x0</Value>

                    <Value index="1">0x14</Value>

                    <Value index="2">0x22</Value>

                    <Value index="3">0x30</Value>

                    <Value index="4">0x3e</Value>

                    <Value index="5">0x4c</Value>

                    <Value index="6">0x5a</Value>

                    <Value index="7">0x68</Value>

                </Format>

                <Format identifier=".amr">

                    <Value index="0">0x0</Value>

                    <Value index="1">0x24</Value>

                    <Value index="2">0x30</Value>

                    <Value index="3">0x3c</Value>

                    <Value index="4">0x47</Value>

                    <Value index="5">0x54</Value>

                    <Value index="6">0x60</Value>

                    <Value index="7">0x6d</Value>

                </Format>

                <Format identifier=".DEFAULT">

                    <Value index="0">0x0</Value>

                    <Value index="1">0x14</Value>

                    <Value index="2">0x22</Value>

                    <Value index="3">0x30</Value>

                    <Value index="4">0x3e</Value>

                    <Value index="5">0x4c</Value>

                    <Value index="6">0x5a</Value>

                    <Value index="7">0x68</Value>

                </Format>

                <Format identifier=".mid">

                    <Value index="0">0x0</Value>

                    <Value index="1">0x24</Value>

                    <Value index="2">0x2e</Value>

                    <Value index="3">0x38</Value>

                    <Value index="4">0x42</Value>

                    <Value index="5">0x4c</Value>

                    <Value index="6">0x58</Value>

                    <Value index="7">0x64</Value>

                </Format>

            </CombinedDevices>

            <CombinedDevices identifier1="AUDIO_DEVICE_OUT_SPEAKER" identifier2="AUDIO_DEVICE_OUT_WIRED_HEADPHONE">

                <Format identifier=".mp3">

                    <Value index="0">0x0</Value>

                    <Value index="1">0x14</Value>

                    <Value index="2">0x22</Value>

                    <Value index="3">0x30</Value>

                    <Value index="4">0x3e</Value>

                    <Value index="5">0x4c</Value>

                    <Value index="6">0x5a</Value>

                    <Value index="7">0x68</Value>

                </Format>

                <Format identifier=".aac">

                    <Value index="0">0x0</Value>

                    <Value index="1">0x14</Value>

                    <Value index="2">0x22</Value>

                    <Value index="3">0x30</Value>

                    <Value index="4">0x3e</Value>

                    <Value index="5">0x4c</Value>

                    <Value index="6">0x5a</Value>

                    <Value index="7">0x68</Value>

                </Format>

                <Format identifier=".ogg">

                    <Value index="0">0x0</Value>

                    <Value index="1">0x14</Value>

                    <Value index="2">0x22</Value>

                    <Value index="3">0x30</Value>

                    <Value index="4">0x3e</Value>

                    <Value index="5">0x4c</Value>

                    <Value index="6">0x5a</Value>

                    <Value index="7">0x68</Value>

                </Format>

                <Format identifier=".amr">

                    <Value index="0">0x0</Value>

                    <Value index="1">0x24</Value>

                    <Value index="2">0x30</Value>

                    <Value index="3">0x3c</Value>

                    <Value index="4">0x47</Value>

                    <Value index="5">0x54</Value>

                    <Value index="6">0x60</Value>

                    <Value index="7">0x6d</Value>

                </Format>

                <Format identifier=".DEFAULT">

                    <Value index="0">0x0</Value>

                    <Value index="1">0x14</Value>

                    <Value index="2">0x22</Value>

                    <Value index="3">0x30</Value>

                    <Value index="4">0x3e</Value>

                    <Value index="5">0x4c</Value>

                    <Value index="6">0x5a</Value>

                    <Value index="7">0x68</Value>

                </Format>

                <Format identifier=".mid">

                    <Value index="0">0x0</Value>

                    <Value index="1">0x24</Value>

                    <Value index="2">0x2e</Value>

                    <Value index="3">0x38</Value>

                    <Value index="4">0x42</Value>

                    <Value index="5">0x4c</Value>

                    <Value index="6">0x58</Value>

                    <Value index="7">0x64</Value>

                </Format>

            </CombinedDevices>

        </Stream>
        <Stream identifier="AUDIO_STREAM_MUSIC" range="0:15">

            <Device identifier="AUDIO_DEVICE_OUT_WIRED_HEADSET">

                <Format identifier=".amr">

                    <Value index="0">0x0</Value>

                    <Value index="1">0xe</Value>

                    <Value index="2">0x1a</Value>

                    <Value index="3">0x26</Value>

                    <Value index="4">0x30</Value>

                    <Value index="5">0x3a</Value>

                    <Value index="6">0x40</Value>

                    <Value index="7">0x46</Value>

                    <Value index="8">0x4a</Value>

                    <Value index="9">0x4e</Value>

                    <Value index="10">0x52</Value>

                    <Value index="11">0x56</Value>

                    <Value index="12">0x5a</Value>

                    <Value index="13">0x5e</Value>

                    <Value index="14">0x64</Value>

                    <Value index="15">0x6a</Value>

                </Format>

                <Format identifier=".3ga">

                    <Value index="0">0x0</Value>

                    <Value index="1">0xe</Value>

                    <Value index="2">0x1a</Value>

                    <Value index="3">0x26</Value>

                    <Value index="4">0x30</Value>

                    <Value index="5">0x3a</Value>

                    <Value index="6">0x40</Value>

                    <Value index="7">0x46</Value>

                    <Value index="8">0x4a</Value>

                    <Value index="9">0x4e</Value>

                    <Value index="10">0x52</Value>

                    <Value index="11">0x56</Value>

                    <Value index="12">0x5a</Value>

                    <Value index="13">0x5e</Value>

                    <Value index="14">0x64</Value>

                    <Value index="15">0x6a</Value>

                </Format>

                <Format identifier=".m4a">

                    <Value index="0">0x0</Value>

                    <Value index="1">0xe</Value>

                    <Value index="2">0x1a</Value>

                    <Value index="3">0x26</Value>

                    <Value index="4">0x30</Value>

                    <Value index="5">0x3a</Value>

                    <Value index="6">0x40</Value>

                    <Value index="7">0x46</Value>

                    <Value index="8">0x4a</Value>

                    <Value index="9">0x4e</Value>

                    <Value index="10">0x52</Value>

                    <Value index="11">0x56</Value>

                    <Value index="12">0x5a</Value>

                    <Value index="13">0x5e</Value>

                    <Value index="14">0x64</Value>

                    <Value index="15">0x6a</Value>

                </Format>

                <Format identifier=".ogg">

                    <Value index="0">0x0</Value>

                    <Value index="1">0xe</Value>

                    <Value index="2">0x1a</Value>

                    <Value index="3">0x26</Value>

                    <Value index="4">0x30</Value>

                    <Value index="5">0x3a</Value>

                    <Value index="6">0x40</Value>

                    <Value index="7">0x46</Value>

                    <Value index="8">0x4a</Value>

                    <Value index="9">0x4e</Value>

                    <Value index="10">0x52</Value>

                    <Value index="11">0x56</Value>

                    <Value index="12">0x5a</Value>

                    <Value index="13">0x5e</Value>

                    <Value index="14">0x64</Value>

                    <Value index="15">0x6a</Value>

                </Format>

                <Format identifier=".wav">

                    <Value index="0">0x0</Value>

                    <Value index="1">0xe</Value>

                    <Value index="2">0x1a</Value>

                    <Value index="3">0x26</Value>

                    <Value index="4">0x30</Value>

                    <Value index="5">0x3a</Value>

                    <Value index="6">0x40</Value>

                    <Value index="7">0x46</Value>

                    <Value index="8">0x4a</Value>

                    <Value index="9">0x4e</Value>

                    <Value index="10">0x52</Value>

                    <Value index="11">0x56</Value>

                    <Value index="12">0x5a</Value>

                    <Value index="13">0x5e</Value>

                    <Value index="14">0x64</Value>

                    <Value index="15">0x6a</Value>

                </Format>

                <Format identifier=".rmvb">

                    <Value index="0">0x0</Value>

                    <Value index="1">0xe</Value>

                    <Value index="2">0x1a</Value>

                    <Value index="3">0x26</Value>

                    <Value index="4">0x30</Value>

                    <Value index="5">0x3a</Value>

                    <Value index="6">0x40</Value>

                    <Value index="7">0x46</Value>

                    <Value index="8">0x4a</Value>

                    <Value index="9">0x4e</Value>

                    <Value index="10">0x52</Value>

                    <Value index="11">0x56</Value>

                    <Value index="12">0x5a</Value>

                    <Value index="13">0x5e</Value>

                    <Value index="14">0x64</Value>

                    <Value index="15">0x6a</Value>

                </Format>

                <Format identifier=".mid">

                    <Value index="0">0x0</Value>

                    <Value index="1">0xe</Value>

                    <Value index="2">0x1a</Value>

                    <Value index="3">0x26</Value>

                    <Value index="4">0x30</Value>

                    <Value index="5">0x3a</Value>

                    <Value index="6">0x40</Value>

                    <Value index="7">0x46</Value>

                    <Value index="8">0x4a</Value>

                    <Value index="9">0x4e</Value>

                    <Value index="10">0x52</Value>

                    <Value index="11">0x56</Value>

                    <Value index="12">0x5a</Value>

                    <Value index="13">0x5e</Value>

                    <Value index="14">0x64</Value>

                    <Value index="15">0x6a</Value>

                </Format>

                <Format identifier=".aac">

                    <Value index="0">0x0</Value>

                    <Value index="1">0xe</Value>

                    <Value index="2">0x1a</Value>

                    <Value index="3">0x26</Value>

                    <Value index="4">0x30</Value>

                    <Value index="5">0x3a</Value>

                    <Value index="6">0x40</Value>

                    <Value index="7">0x46</Value>

                    <Value index="8">0x4a</Value>

                    <Value index="9">0x4e</Value>

                    <Value index="10">0x52</Value>

                    <Value index="11">0x56</Value>

                    <Value index="12">0x5a</Value>

                    <Value index="13">0x5e</Value>

                    <Value index="14">0x64</Value>

                    <Value index="15">0x6a</Value>

                </Format>

                <Format identifier=".mp3">

                    <Value index="0">0x0</Value>

                    <Value index="1">0xe</Value>

                    <Value index="2">0x1a</Value>

                    <Value index="3">0x26</Value>

                    <Value index="4">0x30</Value>

                    <Value index="5">0x3a</Value>

                    <Value index="6">0x40</Value>

                    <Value index="7">0x46</Value>

                    <Value index="8">0x4a</Value>

                    <Value index="9">0x4e</Value>

                    <Value index="10">0x52</Value>

                    <Value index="11">0x56</Value>

                    <Value index="12">0x5a</Value>

                    <Value index="13">0x5e</Value>

                    <Value index="14">0x64</Value>

                    <Value index="15">0x6a</Value>

                </Format>

                <Format identifier=".3gp">

                    <Value index="0">0x0</Value>

                    <Value index="1">0x6</Value>

                    <Value index="2">0x12</Value>

                    <Value index="3">0x1e</Value>

                    <Value index="4">0x28</Value>

                    <Value index="5">0x32</Value>

                    <Value index="6">0x38</Value>

                    <Value index="7">0x3e</Value>

                    <Value index="8">0x42</Value>

                    <Value index="9">0x46</Value>

                    <Value index="10">0x4a</Value>

                    <Value index="11">0x4e</Value>

                    <Value index="12">0x52</Value>

                    <Value index="13">0x56</Value>

                    <Value index="14">0x5c</Value>

                    <Value index="15">0x62</Value>

                </Format>

                <Format identifier=".DEFAULT">
                    <Value index="0">0x0</Value>

                    <Value index="1">0xe</Value>

                    <Value index="2">0x1a</Value>

                    <Value index="3">0x26</Value>

                    <Value index="4">0x30</Value>

                    <Value index="5">0x3a</Value>

                    <Value index="6">0x40</Value>

                    <Value index="7">0x46</Value>

                    <Value index="8">0x4a</Value>

                    <Value index="9">0x4e</Value>

                    <Value index="10">0x52</Value>

                    <Value index="11">0x56</Value>

                    <Value index="12">0x5a</Value>

                    <Value index="13">0x5e</Value>

                    <Value index="14">0x64</Value>

                    <Value index="15">0x6a</Value>

                </Format>
            </Device>
            <Device identifier="AUDIO_DEVICE_OUT_WIRED_HEADPHONE">

                <Format identifier=".mp3">

                    <Value index="0">0x0</Value>

                    <Value index="1">0xe</Value>

                    <Value index="2">0x1a</Value>

                    <Value index="3">0x26</Value>

                    <Value index="4">0x30</Value>

                    <Value index="5">0x3a</Value>

                    <Value index="6">0x40</Value>

                    <Value index="7">0x46</Value>

                    <Value index="8">0x4a</Value>

                    <Value index="9">0x4e</Value>

                    <Value index="10">0x52</Value>

                    <Value index="11">0x56</Value>

                    <Value index="12">0x5a</Value>

                    <Value index="13">0x5e</Value>

                    <Value index="14">0x64</Value>

                    <Value index="15">0x6a</Value>

                </Format>

                <Format identifier=".DEFAULT">
                    <Value index="0">0x0</Value>

                    <Value index="1">0xe</Value>

                    <Value index="2">0x1a</Value>

                    <Value index="3">0x26</Value>

                    <Value index="4">0x30</Value>

                    <Value index="5">0x3a</Value>

                    <Value index="6">0x40</Value>

                    <Value index="7">0x46</Value>

                    <Value index="8">0x4a</Value>

                    <Value index="9">0x4e</Value>

                    <Value index="10">0x52</Value>

                    <Value index="11">0x56</Value>

                    <Value index="12">0x5a</Value>

                    <Value index="13">0x5e</Value>

                    <Value index="14">0x64</Value>

                    <Value index="15">0x6a</Value>

                </Format>

                <Format identifier=".3gp">

                    <Value index="0">0x0</Value>

                    <Value index="1">0x6</Value>

                    <Value index="2">0x12</Value>

                    <Value index="3">0x1e</Value>

                    <Value index="4">0x28</Value>

                    <Value index="5">0x32</Value>

                    <Value index="6">0x38</Value>

                    <Value index="7">0x3e</Value>

                    <Value index="8">0x42</Value>

                    <Value index="9">0x46</Value>

                    <Value index="10">0x4a</Value>

                    <Value index="11">0x4e</Value>

                    <Value index="12">0x52</Value>

                    <Value index="13">0x56</Value>

                    <Value index="14">0x5c</Value>

                    <Value index="15">0x62</Value>

                </Format>

                <Format identifier=".wma">

                    <Value index="0">0x0</Value>

                    <Value index="1">0xe</Value>

                    <Value index="2">0x1a</Value>

                    <Value index="3">0x26</Value>

                    <Value index="4">0x30</Value>

                    <Value index="5">0x3a</Value>

                    <Value index="6">0x40</Value>

                    <Value index="7">0x46</Value>

                    <Value index="8">0x4a</Value>

                    <Value index="9">0x4e</Value>

                    <Value index="10">0x52</Value>

                    <Value index="11">0x56</Value>

                    <Value index="12">0x5a</Value>

                    <Value index="13">0x5e</Value>

                    <Value index="14">0x64</Value>

                    <Value index="15">0x6a</Value>

                </Format>
            </Device>
            <Device identifier="AUDIO_DEVICE_OUT_SPEAKER">

                <Format identifier=".3ga">

                   <Value index="0">0x0</Value>

                    <Value index="1">0x20</Value>

                    <Value index="2">0x26</Value>

                    <Value index="3">0x2c</Value>

                    <Value index="4">0x32</Value>

                    <Value index="5">0x38</Value>

                    <Value index="6">0x3e</Value>

                    <Value index="7">0x44</Value>

                    <Value index="8">0x4a</Value>

                    <Value index="9">0x50</Value>

                    <Value index="10">0x56</Value>

                    <Value index="11">0x5c</Value>

                    <Value index="12">0x62</Value>

                    <Value index="13">0x69</Value>

                    <Value index="14">0x6f</Value>

                    <Value index="15">0x78</Value>

                </Format>

                <Format identifier=".rmvb">

                    <Value index="0">0x0</Value>

                    <Value index="1">0x20</Value>

                    <Value index="2">0x26</Value>

                    <Value index="3">0x2c</Value>

                    <Value index="4">0x32</Value>

                    <Value index="5">0x38</Value>

                    <Value index="6">0x3e</Value>

                    <Value index="7">0x44</Value>

                    <Value index="8">0x4a</Value>

                    <Value index="9">0x50</Value>

                    <Value index="10">0x56</Value>

                    <Value index="11">0x5c</Value>

                    <Value index="12">0x62</Value>

                    <Value index="13">0x69</Value>

                    <Value index="14">0x6f</Value>

                    <Value index="15">0x78</Value>

                </Format>

                <Format identifier=".ogg">

                   <Value index="0">0x0</Value>

                    <Value index="1">0x20</Value>

                    <Value index="2">0x26</Value>

                    <Value index="3">0x2c</Value>

                    <Value index="4">0x32</Value>

                    <Value index="5">0x38</Value>

                    <Value index="6">0x3e</Value>

                    <Value index="7">0x44</Value>

                    <Value index="8">0x4a</Value>

                    <Value index="9">0x50</Value>

                    <Value index="10">0x56</Value>

                    <Value index="11">0x5c</Value>

                    <Value index="12">0x62</Value>

                    <Value index="13">0x69</Value>

                    <Value index="14">0x6f</Value>

                    <Value index="15">0x78</Value>

                </Format>

                <Format identifier=".amr">

                    <Value index="0">0x0</Value>

                    <Value index="1">0x20</Value>

                    <Value index="2">0x26</Value>

                    <Value index="3">0x2c</Value>

                    <Value index="4">0x32</Value>

                    <Value index="5">0x38</Value>

                    <Value index="6">0x3e</Value>

                    <Value index="7">0x44</Value>

                    <Value index="8">0x4a</Value>

                    <Value index="9">0x50</Value>

                    <Value index="10">0x56</Value>

                    <Value index="11">0x5c</Value>

                    <Value index="12">0x62</Value>

                    <Value index="13">0x69</Value>

                    <Value index="14">0x6f</Value>

                    <Value index="15">0x78</Value>

                </Format>

                <Format identifier=".wav">

                   <Value index="0">0x0</Value>

                    <Value index="1">0x20</Value>

                    <Value index="2">0x26</Value>

                    <Value index="3">0x2c</Value>

                    <Value index="4">0x32</Value>

                    <Value index="5">0x38</Value>

                    <Value index="6">0x3e</Value>

                    <Value index="7">0x44</Value>

                    <Value index="8">0x4a</Value>

                    <Value index="9">0x50</Value>

                    <Value index="10">0x56</Value>

                    <Value index="11">0x5c</Value>

                    <Value index="12">0x62</Value>

                    <Value index="13">0x69</Value>

                    <Value index="14">0x6f</Value>

                    <Value index="15">0x78</Value>

                </Format>

                <Format identifier=".wma">

                    <Value index="0">0x0</Value>

                    <Value index="1">0x20</Value>

                    <Value index="2">0x26</Value>

                    <Value index="3">0x2c</Value>

                    <Value index="4">0x32</Value>

                    <Value index="5">0x38</Value>

                    <Value index="6">0x3e</Value>

                    <Value index="7">0x44</Value>

                    <Value index="8">0x4a</Value>

                    <Value index="9">0x50</Value>

                    <Value index="10">0x56</Value>

                    <Value index="11">0x5c</Value>

                    <Value index="12">0x62</Value>

                    <Value index="13">0x69</Value>

                    <Value index="14">0x6f</Value>

                    <Value index="15">0x78</Value>

                </Format>

                <Format identifier=".m4a">

                    <Value index="0">0x0</Value>

                    <Value index="1">0x20</Value>

                    <Value index="2">0x26</Value>

                    <Value index="3">0x2c</Value>

                    <Value index="4">0x32</Value>

                    <Value index="5">0x38</Value>

                    <Value index="6">0x3e</Value>

                    <Value index="7">0x44</Value>

                    <Value index="8">0x4a</Value>

                    <Value index="9">0x50</Value>

                    <Value index="10">0x56</Value>

                    <Value index="11">0x5c</Value>

                    <Value index="12">0x62</Value>

                    <Value index="13">0x69</Value>

                    <Value index="14">0x6f</Value>

                    <Value index="15">0x78</Value>

                </Format>

                <Format identifier=".mid">

                    <Value index="0">0x0</Value>

                    <Value index="1">0x20</Value>

                    <Value index="2">0x26</Value>

                    <Value index="3">0x2c</Value>

                    <Value index="4">0x32</Value>

                    <Value index="5">0x38</Value>

                    <Value index="6">0x3e</Value>

                    <Value index="7">0x44</Value>

                    <Value index="8">0x4a</Value>

                    <Value index="9">0x50</Value>

                    <Value index="10">0x56</Value>

                    <Value index="11">0x5c</Value>

                    <Value index="12">0x62</Value>

                    <Value index="13">0x69</Value>

                    <Value index="14">0x6f</Value>

                    <Value index="15">0x78</Value>

                </Format>

                <Format identifier=".DEFAULT">
                    <Value index="0">0x0</Value>

                    <Value index="1">0x20</Value>

                    <Value index="2">0x26</Value>

                    <Value index="3">0x2c</Value>

                    <Value index="4">0x32</Value>

                    <Value index="5">0x38</Value>

                    <Value index="6">0x3e</Value>

                    <Value index="7">0x44</Value>

                    <Value index="8">0x4a</Value>

                    <Value index="9">0x50</Value>

                    <Value index="10">0x56</Value>

                    <Value index="11">0x5c</Value>

                    <Value index="12">0x62</Value>

                    <Value index="13">0x69</Value>

                    <Value index="14">0x6f</Value>

                    <Value index="15">0x78</Value>

                </Format>

                <Format identifier=".aac">

                    <Value index="0">0x0</Value>

                    <Value index="1">0x20</Value>

                    <Value index="2">0x26</Value>

                    <Value index="3">0x2c</Value>

                    <Value index="4">0x32</Value>

                    <Value index="5">0x38</Value>

                    <Value index="6">0x3e</Value>

                    <Value index="7">0x44</Value>

                    <Value index="8">0x4a</Value>

                    <Value index="9">0x50</Value>

                    <Value index="10">0x56</Value>

                    <Value index="11">0x5c</Value>

                    <Value index="12">0x62</Value>

                    <Value index="13">0x69</Value>

                    <Value index="14">0x6f</Value>

                    <Value index="15">0x78</Value>

                </Format>

                <Format identifier=".mp3">

                    <Value index="0">0x0</Value>

                    <Value index="1">0x20</Value>

                    <Value index="2">0x26</Value>

                    <Value index="3">0x2c</Value>

                    <Value index="4">0x32</Value>

                    <Value index="5">0x38</Value>

                    <Value index="6">0x3e</Value>

                    <Value index="7">0x44</Value>

                    <Value index="8">0x4a</Value>

                    <Value index="9">0x50</Value>

                    <Value index="10">0x56</Value>

                    <Value index="11">0x5c</Value>

                    <Value index="12">0x62</Value>

                    <Value index="13">0x69</Value>

                    <Value index="14">0x6f</Value>

                    <Value index="15">0x78</Value>

                </Format>

            </Device>

            <Device identifier="AUDIO_DEVICE_OUT_BLUETOOTH_A2DP">

                <Format identifier=".mp3">

                    <Value index="0">0x0</Value>

                    <Value index="1">0x24</Value>

                    <Value index="2">0x2a</Value>

                    <Value index="3">0x30</Value>

                    <Value index="4">0x36</Value>

                    <Value index="5">0x3c</Value>

                    <Value index="6">0x42</Value>

                    <Value index="7">0x48</Value>

                    <Value index="8">0x4e</Value>

                    <Value index="9">0x54</Value>

                    <Value index="10">0x5a</Value>

                    <Value index="11">0x60</Value>

                    <Value index="12">0x66</Value>

                    <Value index="13">0x6c</Value>

                    <Value index="14">0x72</Value>

                    <Value index="15">0x78</Value>

                </Format>
            </Device>
        </Stream>
        <Stream identifier="AUDIO_STREAM_NOTIFICATION">
            <CombinedDevices identifier1="AUDIO_DEVICE_OUT_SPEAKER" identifier2="AUDIO_DEVICE_OUT_WIRED_HEADSET">

                <Format identifier=".amr">

                    <Value index="0">0x0</Value>

                    <Value index="1">0x36</Value>

                    <Value index="2">0x3e</Value>

                    <Value index="3">0x46</Value>

                    <Value index="4">0x4e</Value>

                    <Value index="5">0x56</Value>

                    <Value index="6">0x5e</Value>

                    <Value index="7">0x66</Value>

                </Format>

                <Format identifier=".wav">

                    <Value index="0">0x0</Value>

                    <Value index="1">0x36</Value>

                    <Value index="2">0x3e</Value>

                    <Value index="3">0x46</Value>

                    <Value index="4">0x4e</Value>

                    <Value index="5">0x56</Value>

                    <Value index="6">0x5e</Value>

                    <Value index="7">0x66</Value>

                </Format>

                <Format identifier=".mp3">

                    <Value index="0">0x0</Value>

                    <Value index="1">0x36</Value>

                    <Value index="2">0x3e</Value>

                    <Value index="3">0x46</Value>

                    <Value index="4">0x4e</Value>

                    <Value index="5">0x56</Value>

                    <Value index="6">0x5e</Value>

                    <Value index="7">0x66</Value>

                </Format>

                <Format identifier=".aac">

                    <Value index="0">0x0</Value>

                    <Value index="1">0x36</Value>

                    <Value index="2">0x3e</Value>

                    <Value index="3">0x46</Value>

                    <Value index="4">0x4e</Value>

                    <Value index="5">0x56</Value>

                    <Value index="6">0x5e</Value>

                    <Value index="7">0x66</Value>

                </Format>

                <Format identifier=".mid">

                    <Value index="0">0x0</Value>

                    <Value index="1">0x36</Value>

                    <Value index="2">0x3e</Value>

                    <Value index="3">0x46</Value>

                    <Value index="4">0x4e</Value>

                    <Value index="5">0x56</Value>

                    <Value index="6">0x5e</Value>

                    <Value index="7">0x66</Value>

                </Format>

                <Format identifier=".DEFAULT">
                    <Value index="0">0x0</Value>

                    <Value index="1">0x36</Value>

                    <Value index="2">0x3e</Value>

                    <Value index="3">0x46</Value>

                    <Value index="4">0x4e</Value>

                    <Value index="5">0x56</Value>

                    <Value index="6">0x5e</Value>

                    <Value index="7">0x66</Value>

                </Format>

                <Format identifier=".ogg">

                    <Value index="0">0x0</Value>

                    <Value index="1">0x36</Value>

                    <Value index="2">0x3e</Value>

                    <Value index="3">0x46</Value>

                    <Value index="4">0x4e</Value>

                    <Value index="5">0x56</Value>

                    <Value index="6">0x5e</Value>

                    <Value index="7">0x66</Value>

                </Format>

            </CombinedDevices>

            <Device identifier="AUDIO_DEVICE_OUT_WIRED_HEADSET">

                <Format identifier=".ogg">

                    <Value index="0">0x0</Value>

                    <Value index="1">0x11</Value>

                    <Value index="2">0x22</Value>

                    <Value index="3">0x33</Value>

                    <Value index="4">0x44</Value>

                    <Value index="5">0x55</Value>

                    <Value index="6">0x66</Value>

                    <Value index="7">0x64</Value>

                </Format>

            </Device>

            <Device identifier="AUDIO_DEVICE_OUT_SPEAKER">

                <Format identifier=".ogg">

                    <Value index="0">0x0</Value>

                    <Value index="1">0x3c</Value>

                    <Value index="2">0x46</Value>

                    <Value index="3">0x50</Value>

                    <Value index="4">0x5a</Value>

                    <Value index="5">0x64</Value>

                    <Value index="6">0x6e</Value>

                    <Value index="7">0x78</Value>

                </Format>

                <Format identifier=".mp3">

                    <Value index="0">0x0</Value>

                    <Value index="1">0x3c</Value>

                    <Value index="2">0x46</Value>

                    <Value index="3">0x50</Value>

                    <Value index="4">0x5a</Value>

                    <Value index="5">0x64</Value>

                    <Value index="6">0x6e</Value>

                    <Value index="7">0x78</Value>

                </Format>

                <Format identifier=".aac">

                    <Value index="0">0x0</Value>

                    <Value index="1">0x3c</Value>

                    <Value index="2">0x46</Value>

                    <Value index="3">0x50</Value>

                    <Value index="4">0x5a</Value>

                    <Value index="5">0x64</Value>

                    <Value index="6">0x6e</Value>

                    <Value index="7">0x78</Value>

                </Format>

                <Format identifier=".mid">

                    <Value index="0">0x0</Value>

                    <Value index="1">0x3c</Value>

                    <Value index="2">0x46</Value>

                    <Value index="3">0x50</Value>

                    <Value index="4">0x5a</Value>

                    <Value index="5">0x64</Value>

                    <Value index="6">0x6e</Value>

                    <Value index="7">0x78</Value>

                </Format>

                <Format identifier=".wav">

                    <Value index="0">0x0</Value>

                    <Value index="1">0x3c</Value>

                    <Value index="2">0x46</Value>

                    <Value index="3">0x50</Value>

                    <Value index="4">0x5a</Value>

                    <Value index="5">0x64</Value>

                    <Value index="6">0x6e</Value>

                    <Value index="7">0x78</Value>

                </Format>

                <Format identifier=".amr">

                    <Value index="0">0x0</Value>

                    <Value index="1">0x3c</Value>

                    <Value index="2">0x46</Value>

                    <Value index="3">0x50</Value>

                    <Value index="4">0x5a</Value>

                    <Value index="5">0x64</Value>

                    <Value index="6">0x6e</Value>

                    <Value index="7">0x78</Value>

                </Format>
            </Device>
            <CombinedDevices identifier1="AUDIO_DEVICE_OUT_SPEAKER" identifier2="AUDIO_DEVICE_OUT_WIRED_HEADPHONE">

                <Format identifier=".amr">

                    <Value index="0">0x0</Value>

                    <Value index="1">0x36</Value>

                    <Value index="2">0x3e</Value>

                    <Value index="3">0x46</Value>

                    <Value index="4">0x4e</Value>

                    <Value index="5">0x56</Value>

                    <Value index="6">0x5e</Value>

                    <Value index="7">0x66</Value>

                </Format>

                <Format identifier=".wav">

                    <Value index="0">0x0</Value>

                    <Value index="1">0x36</Value>

                    <Value index="2">0x3e</Value>

                    <Value index="3">0x46</Value>

                    <Value index="4">0x4e</Value>

                    <Value index="5">0x56</Value>

                    <Value index="6">0x5e</Value>

                    <Value index="7">0x66</Value>

                </Format>

                <Format identifier=".mp3">

                    <Value index="0">0x0</Value>

                    <Value index="1">0x36</Value>

                    <Value index="2">0x3e</Value>

                    <Value index="3">0x46</Value>

                    <Value index="4">0x4e</Value>

                    <Value index="5">0x56</Value>

                    <Value index="6">0x5e</Value>

                    <Value index="7">0x66</Value>

                </Format>

                <Format identifier=".aac">

                    <Value index="0">0x0</Value>

                    <Value index="1">0x36</Value>

                    <Value index="2">0x3e</Value>

                    <Value index="3">0x46</Value>

                    <Value index="4">0x4e</Value>

                    <Value index="5">0x56</Value>

                    <Value index="6">0x5e</Value>

                    <Value index="7">0x66</Value>

                </Format>

                <Format identifier=".mid">

                    <Value index="0">0x0</Value>

                    <Value index="1">0x36</Value>

                    <Value index="2">0x3e</Value>

                    <Value index="3">0x46</Value>

                    <Value index="4">0x4e</Value>

                    <Value index="5">0x56</Value>

                    <Value index="6">0x5e</Value>

                    <Value index="7">0x66</Value>

                </Format>

                <Format identifier=".DEFAULT">

                    <Value index="0">0x0</Value>

                    <Value index="1">0x36</Value>

                    <Value index="2">0x3e</Value>

                    <Value index="3">0x46</Value>

                    <Value index="4">0x4e</Value>

                    <Value index="5">0x56</Value>

                    <Value index="6">0x5e</Value>

                    <Value index="7">0x66</Value>

                </Format>

                <Format identifier=".ogg">

                    <Value index="0">0x0</Value>

                    <Value index="1">0x36</Value>

                    <Value index="2">0x3e</Value>

                    <Value index="3">0x46</Value>

                    <Value index="4">0x4e</Value>

                    <Value index="5">0x56</Value>

                    <Value index="6">0x5e</Value>

                    <Value index="7">0x66</Value>

                </Format>

            </CombinedDevices>

        </Stream>
        <Stream identifier="AUDIO_STREAM_ALARM">

            <CombinedDevices identifier1="AUDIO_DEVICE_OUT_SPEAKER" identifier2="AUDIO_DEVICE_OUT_WIRED_HEADSET">

                <Format identifier=".DEFAULT">
                    <Value index="0">0x0</Value>

                    <Value index="1">0x14</Value>

                    <Value index="2">0x22</Value>

                    <Value index="3">0x30</Value>

                    <Value index="4">0x3e</Value>

                    <Value index="5">0x4c</Value>

                    <Value index="6">0x5a</Value>

                    <Value index="7">0x66</Value>

                </Format>

                <Format identifier=".mp3">

                    <Value index="0">0x0</Value>

                    <Value index="1">0x14</Value>

                    <Value index="2">0x22</Value>

                    <Value index="3">0x30</Value>

                    <Value index="4">0x3e</Value>

                    <Value index="5">0x4c</Value>

                    <Value index="6">0x5a</Value>

                    <Value index="7">0x66</Value>

                </Format>

                <Format identifier=".aac">

                    <Value index="0">0x0</Value>

                    <Value index="1">0x14</Value>

                    <Value index="2">0x22</Value>

                    <Value index="3">0x30</Value>

                    <Value index="4">0x3e</Value>

                    <Value index="5">0x4c</Value>

                    <Value index="6">0x5a</Value>

                    <Value index="7">0x66</Value>

                </Format>

                <Format identifier=".amr">

                    <Value index="0">0x0</Value>

                    <Value index="1">0x14</Value>

                    <Value index="2">0x22</Value>

                    <Value index="3">0x30</Value>

                    <Value index="4">0x3e</Value>

                    <Value index="5">0x4c</Value>

                    <Value index="6">0x5a</Value>

                    <Value index="7">0x66</Value>

                </Format>

                <Format identifier=".mid">

                    <Value index="0">0x0</Value>

                    <Value index="1">0x14</Value>

                    <Value index="2">0x22</Value>

                    <Value index="3">0x30</Value>

                    <Value index="4">0x3e</Value>

                    <Value index="5">0x4c</Value>

                    <Value index="6">0x5a</Value>

                    <Value index="7">0x66</Value>

                </Format>

                <Format identifier=".ogg">

                    <Value index="0">0x0</Value>

                    <Value index="1">0x14</Value>

                    <Value index="2">0x22</Value>

                    <Value index="3">0x30</Value>

                    <Value index="4">0x3e</Value>

                    <Value index="5">0x4c</Value>

                    <Value index="6">0x5a</Value>

                    <Value index="7">0x66</Value>

                </Format>

            </CombinedDevices>

            <Format identifier=".mp3">

                <Value index="0">0x0</Value>

                <Value index="1">0xc</Value>

                <Value index="2">0x16</Value>

                <Value index="3">0x1e</Value>

                <Value index="4">0x26</Value>

                <Value index="5">0x2e</Value>

                <Value index="6">0x36</Value>

                <Value index="7">0x3e</Value>

            </Format>

            <CombinedDevices identifier1="AUDIO_DEVICE_OUT_SPEAKER" identifier2="AUDIO_DEVICE_OUT_WIRED_HEADPHONE">

                <Format identifier=".ogg">

                    <Value index="0">0x0</Value>

                    <Value index="1">0x14</Value>

                    <Value index="2">0x22</Value>

                    <Value index="3">0x30</Value>

                    <Value index="4">0x3e</Value>

                    <Value index="5">0x4c</Value>

                    <Value index="6">0x5a</Value>

                    <Value index="7">0x66</Value>

                </Format>

                <Format identifier=".mp3">

                    <Value index="0">0x0</Value>

                    <Value index="1">0x14</Value>

                    <Value index="2">0x22</Value>

                    <Value index="3">0x30</Value>

                    <Value index="4">0x3e</Value>

                    <Value index="5">0x4c</Value>

                    <Value index="6">0x5a</Value>

                    <Value index="7">0x66</Value>

                </Format>

                <Format identifier=".aac">

                    <Value index="0">0x0</Value>

                    <Value index="1">0x14</Value>

                    <Value index="2">0x22</Value>

                    <Value index="3">0x30</Value>

                    <Value index="4">0x3e</Value>

                    <Value index="5">0x4c</Value>

                    <Value index="6">0x5a</Value>

                    <Value index="7">0x66</Value>

                </Format>

                <Format identifier=".amr">

                    <Value index="0">0x0</Value>

                    <Value index="1">0x14</Value>

                    <Value index="2">0x22</Value>

                    <Value index="3">0x30</Value>

                    <Value index="4">0x3e</Value>

                    <Value index="5">0x4c</Value>

                    <Value index="6">0x5a</Value>

                    <Value index="7">0x66</Value>

                </Format>

                <Format identifier=".mid">

                    <Value index="0">0x0</Value>

                    <Value index="1">0x14</Value>

                    <Value index="2">0x22</Value>

                    <Value index="3">0x30</Value>

                    <Value index="4">0x3e</Value>

                    <Value index="5">0x4c</Value>

                    <Value index="6">0x5a</Value>

                    <Value index="7">0x66</Value>

                </Format>

                <Format identifier=".DEFAULT">

                    <Value index="0">0x0</Value>

                    <Value index="1">0x14</Value>

                    <Value index="2">0x22</Value>

                    <Value index="3">0x30</Value>

                    <Value index="4">0x3e</Value>

                    <Value index="5">0x4c</Value>

                    <Value index="6">0x5a</Value>

                    <Value index="7">0x66</Value>

                </Format>
            </CombinedDevices>

            <Format identifier=".mp3">

                <Value index="0">0x0</Value>

                <Value index="1">0xc</Value>

                <Value index="2">0x16</Value>

                <Value index="3">0x1e</Value>

                <Value index="4">0x26</Value>

                <Value index="5">0x2e</Value>

                <Value index="6">0x36</Value>

                <Value index="7">0x3e</Value>

            </Format>

        </Stream>
        <Stream identifier="AUDIO_STREAM_EXT_VOIP_WB">

            <Device identifier="AUDIO_DEVICE_OUT_EARPIECE">

                <Format identifier=".DEFAULT">
                    <Value index="0">0x5a</Value>

                    <Value index="1">0x60</Value>

                    <Value index="2">0x66</Value>

                    <Value index="3">0x6c</Value>

                    <Value index="4">0x72</Value>

                    <Value index="5">0x78</Value>

                </Format>

            </Device>

            <Device identifier="AUDIO_DEVICE_OUT_SPEAKER">

                <Format identifier=".DEFAULT">

                    <Value index="0">0x54</Value>

                    <Value index="1">0x5c</Value>

                    <Value index="2">0x64</Value>

                    <Value index="3">0x6c</Value>

                    <Value index="4">0x74</Value>

                    <Value index="5">0x78</Value>

                </Format>
            </Device>
            <Device identifier="AUDIO_DEVICE_OUT_WIRED_HEADPHONE">

                <Format identifier=".DEFAULT">

                    <Value index="0">0x5a</Value>

                    <Value index="1">0x60</Value>

                    <Value index="2">0x66</Value>

                    <Value index="3">0x6c</Value>

                    <Value index="4">0x72</Value>

                    <Value index="5">0x78</Value>

                </Format>

            </Device>

            <Device identifier="AUDIO_DEVICE_OUT_WIRED_HEADSET">

                <Format identifier=".DEFAULT">
                    <Value index="0">0x5a</Value>

                    <Value index="1">0x60</Value>

                    <Value index="2">0x66</Value>

                    <Value index="3">0x6c</Value>

                    <Value index="4">0x72</Value>

                    <Value index="5">0x78</Value>

                </Format>

            </Device>

        </Stream>

        <Stream identifier="AUDIO_STREAM_EXT_VOIP_NB">

            <Device identifier="AUDIO_DEVICE_OUT_EARPIECE">

                <Format identifier=".DEFAULT">

                    <Value index="0">0x5a</Value>

                    <Value index="1">0x60</Value>

                    <Value index="2">0x66</Value>

                    <Value index="3">0x6c</Value>

                    <Value index="4">0x72</Value>

                    <Value index="5">0x78</Value>

                </Format>
            </Device>
            <Device identifier="AUDIO_DEVICE_OUT_SPEAKER">

                <Format identifier=".DEFAULT">

                    <Value index="0">0x54</Value>

                    <Value index="1">0x5c</Value>

                    <Value index="2">0x64</Value>

                    <Value index="3">0x6c</Value>

                    <Value index="4">0x74</Value>

                    <Value index="5">0x78</Value>

                </Format>

            </Device>

            <Device identifier="AUDIO_DEVICE_OUT_WIRED_HEADPHONE">

                <Format identifier=".DEFAULT">
                    <Value index="0">0x5a</Value>

                    <Value index="1">0x60</Value>

                    <Value index="2">0x66</Value>

                    <Value index="3">0x6c</Value>

                    <Value index="4">0x72</Value>

                    <Value index="5">0x78</Value>

                </Format>

            </Device>

            <Device identifier="AUDIO_DEVICE_OUT_WIRED_HEADSET">

                <Format identifier=".DEFAULT">

                    <Value index="0">0x5a</Value>

                    <Value index="1">0x60</Value>

                    <Value index="2">0x66</Value>

                    <Value index="3">0x6c</Value>

                    <Value index="4">0x72</Value>

                    <Value index="5">0x78</Value>

                </Format>
            </Device>
        </Stream>
        <Stream identifier="AUDIO_STREAM_EXT_VT_WB">

            <Device identifier="AUDIO_DEVICE_OUT_DEFAULT">
                <Format identifier=".DEFAULT">
                    <Value index="0">0x50</Value>

                    <Value index="1">0x58</Value>

                    <Value index="2">0x60</Value>

                    <Value index="3">0x68</Value>

                    <Value index="4">0x70</Value>

                    <Value index="5">0x78</Value>

                </Format>

            </Device>

        </Stream>

        <Stream identifier="AUDIO_STREAM_EXT_VT_NB">

            <Device identifier="AUDIO_DEVICE_OUT_DEFAULT">

                <Format identifier=".DEFAULT">

                    <Value index="0">0x50</Value>

                    <Value index="1">0x58</Value>

                    <Value index="2">0x60</Value>

                    <Value index="3">0x68</Value>

                    <Value index="4">0x70</Value>

                    <Value index="5">0x78</Value>
                </Format>
            </Device>
        </Stream>
        <Stream identifier="AUDIO_STREAM_ENFORCED_AUDIBLE">

            <Device identifier="AUDIO_DEVICE_OUT_WIRED_HEADSET">

                <Format identifier=".ogg">

                    <Value index="0">0x0</Value>

                    <Value index="1">0x22</Value>

                    <Value index="2">0x30</Value>

                    <Value index="3">0x3e</Value>

                    <Value index="4">0x4d</Value>

                    <Value index="5">0x5b</Value>

                    <Value index="6">0x69</Value>

                    <Value index="7">0x78</Value>

                </Format>

            </Device>

        </Stream>

    </PlaybackVolumeConfig>

    <RecordVolumeConfig>

        <AppStyle identifier="AUDIO_APP_VOICE_RECORDER">
            <Device identifier="AUDIO_DEVICE_IN_BUILTIN_MIC">

                <Encoder identifier="AUDIO_ENCODER_DEFAULT">
                    <Value index="0">80</Value>
                </Encoder>
            </Device>
        </AppStyle>
        <AppStyle identifier="AUDIO_APP_CAMCODER">

            <Device identifier="AUDIO_DEVICE_IN_BUILTIN_MIC">

                <Encoder identifier="AUDIO_ENCODER_AMR_NB">

                    <Value index="0">80</Value>
                </Encoder>
            </Device>
        </AppStyle>
        <AppStyle identifier="AUDIO_APP_DEFAULT">

            <Device identifier="AUDIO_DEVICE_IN_DEFAULT">
                <Encoder identifier="AUDIO_ENCODER_DEFAULT">
                    <Value index="0">80</Value>
                </Encoder>
            </Device>
            <Device identifier="AUDIO_DEVICE_IN_BUILTIN_MIC">

                <Encoder identifier="AUDIO_ENCODER_AMR_NB">

                    <Value index="0">0x50</Value>

                </Encoder>

                <Encoder identifier="AUDIO_ENCODER_AAC">

                    <Value index="0">0x50</Value>

                </Encoder>

            </Device>

            <Device identifier="AUDIO_DEVICE_IN_BACK_MIC">

                <Encoder identifier="AUDIO_ENCODER_AAC">

                    <Value index="0">0x50</Value>

                </Encoder>
            </Device>
        </AppStyle>
        <AppStyle identifier="AUDIO_APP_VT_RECORDER">
            <Device identifier="AUDIO_DEVICE_IN_DEFAULT">
                <Encoder identifier="AUDIO_ENCODER_DEFAULT">
                    <Value index="0">80</Value>
                </Encoder>
            </Device>
        </AppStyle>
    </RecordVolumeConfig>
</MarvellSWVolCalibrationConfig>
